gluoncv2/__init__.py
gluoncv2/model_provider.py
gluoncv2/models/__init__.py
gluoncv2/models/airnet.py
gluoncv2/models/airnext.py
gluoncv2/models/alexnet.py
gluoncv2/models/alphapose_coco.py
gluoncv2/models/bagnet.py
gluoncv2/models/bamresnet.py
gluoncv2/models/bisenet.py
gluoncv2/models/bninception.py
gluoncv2/models/cbamresnet.py
gluoncv2/models/centernet.py
gluoncv2/models/cgnet.py
gluoncv2/models/channelnet.py
gluoncv2/models/common.py
gluoncv2/models/condensenet.py
gluoncv2/models/crunet.py
gluoncv2/models/crunetb.py
gluoncv2/models/dabnet.py
gluoncv2/models/danet.py
gluoncv2/models/darknet.py
gluoncv2/models/darknet53.py
gluoncv2/models/darts.py
gluoncv2/models/deeplabv3.py
gluoncv2/models/densenet.py
gluoncv2/models/densenet_cifar.py
gluoncv2/models/diapreresnet.py
gluoncv2/models/diapreresnet_cifar.py
gluoncv2/models/diaresnet.py
gluoncv2/models/diaresnet_cifar.py
gluoncv2/models/dicenet.py
gluoncv2/models/diracnetv2.py
gluoncv2/models/dla.py
gluoncv2/models/dpn.py
gluoncv2/models/drn.py
gluoncv2/models/efficientnet.py
gluoncv2/models/efficientnetedge.py
gluoncv2/models/espnetv2.py
gluoncv2/models/fastscnn.py
gluoncv2/models/fastseresnet.py
gluoncv2/models/fbnet.py
gluoncv2/models/fcn8sd.py
gluoncv2/models/fdmobilenet.py
gluoncv2/models/fishnet.py
gluoncv2/models/fpenet.py
gluoncv2/models/fractalnet_cifar.py
gluoncv2/models/ghostnet.py
gluoncv2/models/hardnet.py
gluoncv2/models/hrnet.py
gluoncv2/models/ibnbresnet.py
gluoncv2/models/ibndensenet.py
gluoncv2/models/ibnresnet.py
gluoncv2/models/ibnresnext.py
gluoncv2/models/ibppose_coco.py
gluoncv2/models/icnet.py
gluoncv2/models/igcv3.py
gluoncv2/models/inceptionresnetv1.py
gluoncv2/models/inceptionresnetv2.py
gluoncv2/models/inceptionv3.py
gluoncv2/models/inceptionv4.py
gluoncv2/models/irevnet.py
gluoncv2/models/isqrtcovresnet.py
gluoncv2/models/jasper.py
gluoncv2/models/jasperdr.py
gluoncv2/models/lednet.py
gluoncv2/models/lffd.py
gluoncv2/models/lwopenpose_cmupan.py
gluoncv2/models/menet.py
gluoncv2-0.0.64.dist-info/LICENSE.txt
gluoncv2-0.0.64.dist-info/METADATA
gluoncv2-0.0.64.dist-info/WHEEL
gluoncv2-0.0.64.dist-info/top_level.txt
gluoncv2-0.0.64.dist-info/RECORD
