Metadata-Version: 2.1
Name: gluoncv2
Version: 0.0.64
Summary: Image classification and segmentation models for Gluon
Home-page: https://github.com/osmr/imgclsmob
Author: Oleg Sémery
Author-email: osemery@gmail.com
License: MIT
Keywords: machine-learning deep-learning neuralnetwork image-classification mxnet gluon imagenet cifar svhn vgg resnet pyramidnet diracnet densenet condensenet wrn drn dpn darknet fishnet espnetv2 hrnet xdensnet squeezenet squeezenext shufflenet menet mobilenet igcv3 mnasnet darts xception inception polynet nasnet pnasnet ror proxylessnas dianet efficientnet mixnet image-segmentation voc ade20k cityscapes coco pspnet deeplabv3 fcn
Platform: UNKNOWN
Classifier: Development Status :: 3 - Alpha
Classifier: Intended Audience :: Science/Research
Classifier: License :: OSI Approved :: MIT License
Classifier: Operating System :: OS Independent
Classifier: Programming Language :: Python
Classifier: Topic :: Scientific/Engineering :: Image Recognition
License-File: LICENSE.txt
Requires-Dist: numpy
